{
  "full_name": "openfootball/europe-champions-league",
  "created_at": "2013-12-14T22:43:21Z",
  "history": {
    "2017-02-11": {
      "stargazers_count": 16
    },
    "2017-02-12": {
      "stargazers_count": 17
    },
    "2017-06-18": {
      "stargazers_count": 19
    },
    "2017-07-28": {
      "stargazers_count": 19
    },
    "2017-12-10": {
      "stargazers_count": 19
    },
    "2018-01-28": {
      "stargazers_count": 19
    },
    "2018-02-08": {
      "stargazers_count": 19
    },
    "2018-02-27": {
      "stargazers_count": 19
    },
    "2018-04-08": {
      "stargazers_count": 19
    },
    "2018-05-18": {
      "stargazers_count": 20
    },
    "2018-09-20": {
      "stargazers_count": 21
    },
    "2018-11-02": {
      "stargazers_count": 22
    },
    "2019-02-01": {
      "stargazers_count": 23
    },
    "2019-04-17": {
      "stargazers_count": 24
    },
    "2019-07-22": {
      "stargazers_count": 24
    },
    "2019-09-29": {
      "stargazers_count": 23
    },
    "2019-12-08": {
      "stargazers_count": 23
    }
  },
  "commits": [
    {
      "committer": {
        "date": "2018-06-18T16:01:23Z",
        "name": "Gerald Bauer"
      },
      "author": {
        "date": "2018-06-18T16:01:23Z",
        "name": "Gerald Bauer"
      },
      "message": "add setups"
    }
  ],
  "size": 123,
  "updated_at": "2019-08-23T19:04:12Z",
  "pushed_at": "2018-06-18T16:01:43Z"
}