{
  "full_name": "planetruby/meetups",
  "created_at": "2018-11-19T18:10:05Z",
  "updated_at": "2020-10-09T01:22:29Z",
  "pushed_at": "2020-10-01T06:38:11Z",
  "size": 34,
  "history": {
    "2019-02-01": {
      "stargazers_count": 8
    },
    "2019-04-17": {
      "stargazers_count": 8
    },
    "2019-07-22": {
      "stargazers_count": 8
    },
    "2019-09-29": {
      "stargazers_count": 8
    },
    "2019-12-08": {
      "stargazers_count": 11
    },
    "2020-06-05": {
      "stargazers_count": 11
    },
    "2020-09-14": {
      "stargazers_count": 11
    },
    "2020-10-09": {
      "stargazers_count": 12
    },
    "2020-10-11": {
      "stargazers_count": 12,
      "forks_count": 5
    }
  },
  "commits": [
    {
      "committer": {
        "date": "2020-10-01T06:38:09Z",
        "name": "GitHub"
      },
      "author": {
        "date": "2020-10-01T06:38:09Z",
        "name": "James Adam"
      },
      "message": "Add NWRUG group to European Ruby User Groups (#7)"
    }
  ],
  "description": "A collection of awesome ruby meetups & orgs from around the world - Add your ruby meetup!",
  "language": null,
  "topics": [

  ],
  "traffic": {
    "summary": {
      "views": {
        "count": 30,
        "uniques": 7
      },
      "clones": {
        "count": 5,
        "uniques": 5
      },
      "paths": [
        {
          "path": "/planetruby/meetups",
          "title": "planetruby/meetups: A collection of awesome ruby meetups & orgs from around t...",
          "count": 12,
          "uniques": 5
        },
        {
          "path": "/planetruby/meetups/pull/7",
          "title": "Add NWRUG group to European Ruby User Groups by lazyatom · Pull Request #7 · ...",
          "count": 6,
          "uniques": 4
        },
        {
          "path": "/planetruby/meetups/pull/7/files",
          "title": "Add NWRUG group to European Ruby User Groups by lazyatom · Pull Request #7 · ...",
          "count": 4,
          "uniques": 3
        },
        {
          "path": "/planetruby/meetups/blob/master/EUROPE.md",
          "title": "meetups/EUROPE.md at master · planetruby/meetups",
          "count": 2,
          "uniques": 2
        },
        {
          "path": "/planetruby/meetups/blob/master/AMERICA.md",
          "title": "meetups/AMERICA.md at master · planetruby/meetups",
          "count": 1,
          "uniques": 1
        },
        {
          "path": "/planetruby/meetups/blob/master/ASIA.md",
          "title": "meetups/ASIA.md at master · planetruby/meetups",
          "count": 1,
          "uniques": 1
        },
        {
          "path": "/planetruby/meetups/blob/master/_config.yml",
          "title": "meetups/_config.yml at master · planetruby/meetups",
          "count": 1,
          "uniques": 1
        },
        {
          "path": "/planetruby/meetups/commit/858419b70b88dacf85c6df8ef10480208ed91f55",
          "title": "Add NWRUG group to European Ruby User Groups (#7) · planetruby/meetups@858419b",
          "count": 1,
          "uniques": 1
        },
        {
          "path": "/planetruby/meetups/compare/master...lazyatom:patch-1",
          "title": "Comparing planetruby:master...lazyatom:patch-1 · planetruby/meetups",
          "count": 1,
          "uniques": 1
        },
        {
          "path": "/planetruby/meetups/edit/master/EUROPE.md",
          "title": "Editing meetups/EUROPE.md at master · planetruby/meetups",
          "count": 1,
          "uniques": 1
        }
      ],
      "referrers": [
        {
          "referrer": "github.com",
          "count": 9,
          "uniques": 5
        },
        {
          "referrer": "planetruby.github.io",
          "count": 1,
          "uniques": 1
        }
      ]
    },
    "history": {
      "2020-09-29": {
        "views": {
          "count": 1,
          "uniques": 1
        }
      },
      "2020-09-30": {
        "views": {
          "count": 8,
          "uniques": 3
        }
      },
      "2020-10-01": {
        "views": {
          "count": 3,
          "uniques": 1
        },
        "clones": {
          "count": 3,
          "uniques": 3
        }
      },
      "2020-10-09": {
        "views": {
          "count": 18,
          "uniques": 3
        },
        "clones": {
          "count": 1,
          "uniques": 1
        }
      },
      "2020-09-28": {
        "clones": {
          "count": 1,
          "uniques": 1
        }
      }
    }
  }
}