{
  "full_name": "publicdomainworks/publicdomainworks.github.io",
  "created_at": "2016-11-15T08:14:55Z",
  "history": {
    "2017-02-11": {
      "stargazers_count": 1
    },
    "2017-02-12": {
      "stargazers_count": 1
    },
    "2017-06-18": {
      "stargazers_count": 1
    },
    "2017-07-28": {
      "stargazers_count": 1
    },
    "2017-12-10": {
      "stargazers_count": 2
    },
    "2018-01-28": {
      "stargazers_count": 2
    },
    "2018-02-08": {
      "stargazers_count": 2
    },
    "2018-02-27": {
      "stargazers_count": 2
    },
    "2018-04-08": {
      "stargazers_count": 2
    },
    "2018-05-18": {
      "stargazers_count": 2
    },
    "2018-09-20": {
      "stargazers_count": 2
    },
    "2018-11-02": {
      "stargazers_count": 2
    },
    "2019-02-01": {
      "stargazers_count": 2
    },
    "2019-04-17": {
      "stargazers_count": 2
    },
    "2019-07-22": {
      "stargazers_count": 2
    },
    "2019-09-29": {
      "stargazers_count": 2
    },
    "2019-12-08": {
      "stargazers_count": 2
    },
    "2020-06-05": {
      "stargazers_count": 2
    },
    "2020-09-14": {
      "stargazers_count": 2
    },
    "2020-10-09": {
      "stargazers_count": 2
    },
    "2020-10-11": {
      "stargazers_count": 2,
      "forks_count": 0
    }
  },
  "commits": [
    {
      "committer": {
        "date": "2016-11-15T08:21:54Z",
        "name": "GitHub"
      },
      "author": {
        "date": "2016-11-15T08:21:54Z",
        "name": "Gerald Bauer"
      },
      "message": "Delete .gitkeep"
    }
  ],
  "size": 2,
  "updated_at": "2017-08-31T14:51:38Z",
  "pushed_at": "2016-11-15T08:21:54Z",
  "description": "Public Domain Works Site",
  "language": null,
  "topics": [

  ],
  "traffic": {
    "summary": {
      "views": {
        "count": 1,
        "uniques": 1
      },
      "clones": {
        "count": 1,
        "uniques": 1
      },
      "paths": [
        {
          "path": "/publicdomainworks/publicdomainworks.github.io",
          "title": "publicdomainworks/publicdomainworks.github.io: Public Domain Works Site",
          "count": 1,
          "uniques": 1
        }
      ],
      "referrers": [
        {
          "referrer": "github.com",
          "count": 1,
          "uniques": 1
        }
      ]
    },
    "history": {
      "2020-10-06": {
        "views": {
          "count": 1,
          "uniques": 1
        }
      },
      "2020-09-28": {
        "clones": {
          "count": 1,
          "uniques": 1
        }
      }
    }
  }
}