{
  "full_name": "rsssf/espana",
  "created_at": "2014-06-03T06:11:33Z",
  "updated_at": "2020-05-13T19:48:10Z",
  "pushed_at": "2015-07-26T10:34:53Z",
  "size": 264,
  "history": {
    "2020-06-05": {
      "stargazers_count": 2
    },
    "2020-09-14": {
      "stargazers_count": 2
    },
    "2020-10-09": {
      "stargazers_count": 2
    },
    "2020-10-11": {
      "stargazers_count": 2,
      "forks_count": 0
    }
  },
  "commits": [
    {
      "committer": {
        "date": "2015-07-26T10:34:47Z",
        "name": "Gerald Bauer"
      },
      "author": {
        "date": "2015-07-26T10:34:47Z",
        "name": "Gerald Bauer"
      },
      "message": "add copa del rey"
    }
  ],
  "description": "football.db RSSSF (Rec.Sport.Soccer Statistics Foundation) Archive Data for España (Spain) / Europe - Primera División / La Liga, etc.",
  "language": null,
  "topics": [

  ],
  "traffic": {
    "summary": {
      "views": {
        "count": 13,
        "uniques": 8
      },
      "clones": {
        "count": 1,
        "uniques": 1
      },
      "paths": [
        {
          "path": "/rsssf/espana",
          "title": "rsssf/espana: football.db RSSSF (Rec.Sport.Soccer Statistics Foundation) Arch...",
          "count": 7,
          "uniques": 7
        },
        {
          "path": "/rsssf/espana/blob/master/2014-15/1-liga.txt",
          "title": "espana/1-liga.txt at master · rsssf/espana · GitHub",
          "count": 2,
          "uniques": 2
        },
        {
          "path": "/rsssf/espana/blob/master/2014-15/cup.txt",
          "title": "espana/cup.txt at master · rsssf/espana · GitHub",
          "count": 1,
          "uniques": 1
        },
        {
          "path": "/rsssf/espana/blob/master/tables/span2015.txt",
          "title": "espana/span2015.txt at master · rsssf/espana · GitHub",
          "count": 1,
          "uniques": 1
        },
        {
          "path": "/rsssf/espana/tree/master/2014-15",
          "title": "espana/2014-15 at master · rsssf/espana · GitHub",
          "count": 1,
          "uniques": 1
        },
        {
          "path": "/rsssf/espana/tree/master/tables",
          "title": "espana/tables at master · rsssf/espana · GitHub",
          "count": 1,
          "uniques": 1
        }
      ],
      "referrers": [
        {
          "referrer": "github.com",
          "count": 7,
          "uniques": 7
        }
      ]
    },
    "history": {
      "2020-09-28": {
        "views": {
          "count": 3,
          "uniques": 1
        },
        "clones": {
          "count": 1,
          "uniques": 1
        }
      },
      "2020-09-29": {
        "views": {
          "count": 1,
          "uniques": 1
        }
      },
      "2020-09-30": {
        "views": {
          "count": 3,
          "uniques": 1
        }
      },
      "2020-10-01": {
        "views": {
          "count": 1,
          "uniques": 1
        }
      },
      "2020-10-03": {
        "views": {
          "count": 2,
          "uniques": 1
        }
      },
      "2020-10-05": {
        "views": {
          "count": 1,
          "uniques": 1
        }
      },
      "2020-10-09": {
        "views": {
          "count": 2,
          "uniques": 2
        }
      }
    }
  }
}